LICENSE
README.md
setup.py
data_cleaner_byzahid/__init__.py
data_cleaner_byzahid/categorical_encoder.py
data_cleaner_byzahid/data_type_converter.py
data_cleaner_byzahid/date_time_handler.py
data_cleaner_byzahid/feature_engineer.py
data_cleaner_byzahid/missing_value_handler.py
data_cleaner_byzahid/outlier_handler.py
data_cleaner_byzahid/scaler.py
data_cleaner_byzahid/text_cleaner.py
data_cleaner_byzahid.egg-info/PKG-INFO
data_cleaner_byzahid.egg-info/SOURCES.txt
data_cleaner_byzahid.egg-info/dependency_links.txt
data_cleaner_byzahid.egg-info/requires.txt
data_cleaner_byzahid.egg-info/top_level.txt
examples/__init__.py
tests/__init__.py
tests/test_categorical_encoder.py
tests/test_data_type_converter.py
tests/test_date_time_handler.py
tests/test_feature_engineer.py
tests/test_missing_value_handler.py
tests/test_outlier_handler.py
tests/test_scaler.py
tests/test_text_cleaner.py