Metadata-Version: 2.1
Name: data_cleaner_byzahid
Version: 0.1.0
Summary: A comprehensive Python library for data preprocessing
Home-page: https://github.com/zahidesad/Data-Cleaner-For-Movie-Recommendation
Download-URL: https://github.com/zahidesad/Data-Cleaner-For-Movie-Recommendation/archive/refs/tags/0.1.0.tar.gz
Author: Zahid Esad Baltacı
Author-email: zahid.bltci@gmail.com
Classifier: Programming Language :: Python :: 3
Classifier: License :: OSI Approved :: MIT License
Classifier: Operating System :: OS Independent
Requires-Python: >=3.6
License-File: LICENSE
Requires-Dist: pandas
Requires-Dist: numpy
Requires-Dist: nltk
Requires-Dist: beautifulsoup4
